alibabacloud_dms_enterprise20181101/__init__.py
alibabacloud_dms_enterprise20181101/client.py
alibabacloud_dms_enterprise20181101/models/__init__.py
alibabacloud_dms_enterprise20181101/models/_add_authority_template_items_request.py
alibabacloud_dms_enterprise20181101/models/_add_authority_template_items_response.py
alibabacloud_dms_enterprise20181101/models/_add_authority_template_items_response_body.py
alibabacloud_dms_enterprise20181101/models/_add_authority_template_items_shrink_request.py
alibabacloud_dms_enterprise20181101/models/_add_desensitization_rule_request.py
alibabacloud_dms_enterprise20181101/models/_add_desensitization_rule_response.py
alibabacloud_dms_enterprise20181101/models/_add_desensitization_rule_response_body.py
alibabacloud_dms_enterprise20181101/models/_add_instance_request.py
alibabacloud_dms_enterprise20181101/models/_add_instance_response.py
alibabacloud_dms_enterprise20181101/models/_add_instance_response_body.py
alibabacloud_dms_enterprise20181101/models/_add_lh_members_request.py
alibabacloud_dms_enterprise20181101/models/_add_lh_members_response.py
alibabacloud_dms_enterprise20181101/models/_add_lh_members_response_body.py
alibabacloud_dms_enterprise20181101/models/_add_lh_members_shrink_request.py
alibabacloud_dms_enterprise20181101/models/_add_logic_table_route_config_request.py
alibabacloud_dms_enterprise20181101/models/_add_logic_table_route_config_response.py
alibabacloud_dms_enterprise20181101/models/_add_logic_table_route_config_response_body.py
alibabacloud_dms_enterprise20181101/models/_add_table_to_category_request.py
alibabacloud_dms_enterprise20181101/models/_add_table_to_category_response.py
alibabacloud_dms_enterprise20181101/models/_add_table_to_category_response_body.py
alibabacloud_dms_enterprise20181101/models/_add_task_flow_edges_request.py
alibabacloud_dms_enterprise20181101/models/_add_task_flow_edges_response.py
alibabacloud_dms_enterprise20181101/models/_add_task_flow_edges_response_body.py
alibabacloud_dms_enterprise20181101-2.1.4.dist-info/LICENSE
alibabacloud_dms_enterprise20181101-2.1.4.dist-info/METADATA
alibabacloud_dms_enterprise20181101-2.1.4.dist-info/WHEEL
alibabacloud_dms_enterprise20181101-2.1.4.dist-info/top_level.txt
alibabacloud_dms_enterprise20181101-2.1.4.dist-info/RECORD
